[
  {
    "img": "uploads/1714056205383_Screenshot_3.jpg",
    "country": "g",
    "publish_date": "0312-03-12",
    "title": "g",
    "content": "g"
  },
  {
    "img": "uploads/1714056568898_Screenshot_9.jpg",
    "country": "საქართველო, სამცხე",
    "publish_date": "2024-06-05",
    "title": "მოგზაურობა სამცხეში",
    "content": "ჩვენ ვიყავით სამცხეში, მაგარია"
  },
  {
    "img": "uploads/1714056594281_Screenshot_9.jpg",
    "country": "საქართველო, სამცხე",
    "publish_date": "2024-06-05",
    "title": "მოგზაურობა სამცხეში",
    "content": "ჩვენ ვიყავით სამცხეში, მაგარია"
  },
  {
    "img": "uploads/1714147108298_Screenshot_6.jpg",
    "country": "gg",
    "publish_date": "1212-12-12",
    "title": "gg",
    "content": "gg"
  },
  {
    "img": null
  }
]